dagsonar/__about__.py
dagsonar/__init__.py
dagsonar/debugger.py
dagsonar/encoder.py
dagsonar/hash.py
dagsonar/models.py
dagsonar/parser.py
dagsonar/tracker.py
dagsonar-0.0.4.dist-info/METADATA
dagsonar-0.0.4.dist-info/WHEEL
dagsonar-0.0.4.dist-info/licenses/LICENSE
dagsonar-0.0.4.dist-info/licenses/LICENSE.txt
dagsonar-0.0.4.dist-info/RECORD
