Metadata-Version: 2.4
Name: dagsonar
Version: 0.0.4
Summary: Deep visibility into your Airflow task changes
Project-URL: Documentation, https://github.com/pesnik/dagsonar#readme
Project-URL: Issues, https://github.com/pesnik/dagsonar/issues
Project-URL: Source, https://github.com/pesnik/dagsonar
Author-email: "Md. Rakibul Hasan" <hasanrakibul.masum@gmail.com>
License-Expression: MIT
License-File: LICENSE
License-File: LICENSE.txt
Keywords: airflow,changes,dag,monitoring,task,tracking
Classifier: Development Status :: 4 - Beta
Classifier: Programming Language :: Python
Classifier: Programming Language :: Python :: 3.8
Classifier: Programming Language :: Python :: 3.9
Classifier: Programming Language :: Python :: 3.10
Classifier: Programming Language :: Python :: 3.11
Classifier: Programming Language :: Python :: 3.12
Classifier: Programming Language :: Python :: Implementation :: CPython
Classifier: Programming Language :: Python :: Implementation :: PyPy
Requires-Python: >=3.8
Requires-Dist: click>=8.0.0
Requires-Dist: rich>=10.0.0
